{"api_dimensions.md":"CXBQiND-","api_lookuparrays.md":"Cm6bQ72V","api_reference.md":"DAfBCTZM","basics.md":"BmACLvN0","broadcasts.md":"qPdHrk-w","cuda.md":"nbIxHCRQ","dimarrays.md":"Bc-NTypl","dimensions.md":"BsKT6Pk8","diskarrays.md":"1Il_hJFy","extending_dd.md":"DZZb_ZjW","get_info.md":"BZJhKLa-","groupby.md":"K6Wkezvt","index.md":"BoD9qA3a","integrations.md":"4wdnJ-hV","object_modification.md":"BMDppNP3","plots.md":"V9NK60QU","selectors.md":"DyVI5TQK","stacks.md":"AYNYyLMs","tables.md":"DFuo_hUi","xarray.md":"4G9fdHl0"}
