{"api_dimensions.md":"Os8yvyT5","api_lookuparrays.md":"C_gJJddc","api_reference.md":"Dbq5Q-Jm","basics.md":"DUte7mCU","broadcasts.md":"DonmjtnK","cuda.md":"BvtLXdnM","dimarrays.md":"baDW8edy","dimensions.md":"0aXz9luM","diskarrays.md":"CCsnT3Eh","extending_dd.md":"Dij_ZZ50","get_info.md":"BZxw4zdm","groupby.md":"DPBGnHhM","index.md":"CMhKXWWC","integrations.md":"B0LwfGAB","object_modification.md":"DWBtIo3l","plots.md":"CTugkKoG","selectors.md":"BY_i7OQT","stacks.md":"qn1NiCn3","tables.md":"CCER1nbM","xarray.md":"BN5ykYxB"}
