{"api_dimensions.md":"yniopdEI","api_lookuparrays.md":"Bg5rU8Jm","api_reference.md":"D1ifx4YZ","basics.md":"BRjP_6uh","broadcasts.md":"Bzv3iQ-l","cuda.md":"CfHfBze2","dimarrays.md":"CHCrH8P2","dimensions.md":"COM96S4s","diskarrays.md":"BEBu8N7e","extending_dd.md":"DanS16yW","get_info.md":"C_RL_y0E","groupby.md":"BaWUFhx5","index.md":"D9KVNUlW","integrations.md":"DkMxpl_T","object_modification.md":"CBd2_E-b","plots.md":"VyDoUgXZ","selectors.md":"DBgOCRT4","stacks.md":"x16Q9RPA","tables.md":"BHw-foRG","xarray.md":"Bf-e74uM"}
